{
  "camera": {
    "frameTimestamp": 1738157737643
  },
  "face_detector": {
    "totalFaces": 1,
    "rects": [
      {
        "y": 49.378845977783214,
        "x": 100.22674293518065,
        "width": 125.87155685424807,
        "height": 160.20016326904295,
        "confidence": 29.31104278564453
      }
    ],
    "faces": [
      {}
    ],
    "status": "INIT",
    "fullFrameDetection": true
  },
  "face_age": {
    "numericAge": 26,
    "age": {
      "_-18": 0,
      "18-35": 1,
      "35-51": 0,
      "51-_": 0
    }
  },
  "face_emotion": {
    "dominantEmotion": "Surprise",
    "emotion": {
      "Angry": 0.04,
      "Disgust": 0.1,
      "Fear": 0.01,
      "Happy": 0.2,
      "Neutral": 0.11,
      "Sad": 0.02,
      "Surprise": 0.52
    }
  },
  "face_gender": {
    "gender": {
      "Female": 0.03,
      "Male": 0.97
    },
    "mostConfident": "Male"
  },
  "face_features": {
    "features": {
      "Arched Eyebrows": 0.03,
      "Attractive": 0.12,
      "Bald": 0.01,
      "Beard 5 O'Clock Shadow": 0.24,
      "Black Hair": 0.37,
      "Blond Hair": 0.01,
      "Brown Hair": 0.06,
      "Earrings": 0.05,
      "Eyebrows Bushy": 0.14,
      "Eyeglasses": 0.85,
      "Goatee": 0.18,
      "Gray Hair": 0,
      "Hat": 0.29,
      "High Cheekbones": 0.31,
      "Lipstick": 0.01,
      "Mustache": 0.15,
      "Narrow Eyes": 0.15,
      "Necklace": 0.04,
      "Necktie": 0.12,
      "Oval Face": 0.27,
      "Pale Skin": 0.04,
      "Rosy Cheeks": 0.01,
      "Sideburns": 0.07,
      "Straight Hair": 0.2,
      "Wavy Hair": 0.07
    }
  },
  "face_pose": {
    "pose": {
      "pitch": 0.03,
      "yaw": 0.12,
      "roll": -0.02
    }
  },
  "face_arousal_valence": {
    "arousal": -0.23,
    "valence": 0.36,
    "affects38": {
      "Afraid": 0,
      "Amused": 0.57,
      "Angry": 0,
      "Annoyed": 0,
      "Anxious": 0,
      "Apathetic": 0.33,
      "Astonished": 0,
      "Bored": 0.02,
      "Calm": 0.3,
      "Conceited": 0.02,
      "Contemplative": 0.68,
      "Content": 0.34,
      "Convinced": 0.16,
      "Delighted": 0.05,
      "Depressed": 0,
      "Determined": 0.23,
      "Disappointed": 0,
      "Discontented": 0,
      "Distressed": 0,
      "Embarrassed": 0.06,
      "Enraged": 0,
      "Excited": 0.01,
      "Feel Well": 0.32,
      "Frustrated": 0,
      "Happy": 0.16,
      "Hopeful": 0.91,
      "Impressed": 0.97,
      "Melancholic": 0.3,
      "Peaceful": 0.29,
      "Pensive": 0.53,
      "Pleased": 0.41,
      "Relaxed": 0.37,
      "Sad": 0,
      "Satisfied": 0.33,
      "Sleepy": 0.04,
      "Tired": 0.03,
      "Uncomfortable": 0,
      "Worried": 0.62
    },
    "affects98": {
      "Adventurous": 0,
      "Afraid": 0,
      "Alarmed": 0,
      "Ambitious": 0.02,
      "Amorous": 0.5,
      "Amused": 0.57,
      "Angry": 0,
      "Annoyed": 0,
      "Anxious": 0,
      "Apathetic": 0.33,
      "Aroused": 0,
      "Ashamed": 0.03,
      "Astonished": 0,
      "At Ease": 0.37,
      "Attentive": 0.92,
      "Bellicose": 0,
      "Bitter": 0,
      "Bored": 0.02,
      "Calm": 0.3,
      "Compassionate": 0.13,
      "Conceited": 0.02,
      "Confident": 0.97,
      "Conscientious": 0.36,
      "Contemplative": 0.68,
      "Contemptuous": 0,
      "Content": 0.34,
      "Convinced": 0.16,
      "Courageous": 0.01,
      "Defient": 0,
      "Dejected": 0,
      "Delighted": 0.05,
      "Depressed": 0,
      "Desperate": 0,
      "Despondent": 0.01,
      "Determined": 0.23,
      "Disappointed": 0,
      "Discontented": 0,
      "Disgusted": 0,
      "Dissatisfied": 0.01,
      "Distressed": 0,
      "Distrustful": 0.02,
      "Doubtful": 0.01,
      "Droopy": 0.01,
      "Embarrassed": 0.06,
      "Enraged": 0,
      "Enthusiastic": 0.33,
      "Envious": 0,
      "Excited": 0.01,
      "Expectant": 0.89,
      "Feel Guilt": 0.05,
      "Feel Well": 0.32,
      "Feeling Superior": 0.05,
      "Friendly": 0.41,
      "Frustrated": 0,
      "Glad": 0.28,
      "Gloomy": 0,
      "Happy": 0.16,
      "Hateful": 0,
      "Hesitant": 0.03,
      "Hopeful": 0.91,
      "Hostile": 0,
      "Impatient": 0.17,
      "Impressed": 0.97,
      "Indignant": 0.02,
      "Insulted": 0,
      "Interested": 0.75,
      "Jealous": 0.02,
      "Joyous": 0.13,
      "Languid": 0.19,
      "Light Hearted": 0.43,
      "Loathing": 0,
      "Longing": 0.93,
      "Lusting": 0,
      "Melancholic": 0.3,
      "Miserable": 0,
      "Passionate": 0.79,
      "Peaceful": 0.29,
      "Pensive": 0.53,
      "Pleased": 0.41,
      "Polite": 0.67,
      "Relaxed": 0.37,
      "Reverent": 0.08,
      "Sad": 0,
      "Satisfied": 0.33,
      "Selfconfident": 0.01,
      "Serene": 0.38,
      "Serious": 0.62,
      "Sleepy": 0.04,
      "Solemn": 0.49,
      "Startled": 0,
      "Suspicious": 0.03,
      "Taken Aback": 0.06,
      "Tense": 0,
      "Tired": 0.03,
      "Triumphant": 0,
      "Uncomfortable": 0,
      "Wavering": 0,
      "Worried": 0.62
    },
    "quadrant": "Conductive"
  },
  "face_attention": {
    "attention": 0.88
  },
  "face_positivity": {
    "positivity": 0.68
  },
  "audio_current_time": null
}